[
  {
    "label": "Activate your card",
    "text": "Activate your card online or by phone.",
    "file": "activate_card.json"
  },
  {
    "label": "Appointment",
    "text": "Provide the user with task appointment details.",
    "file": "appointment.json"
  },
  {
    "label": "Authentication",
    "text": "Prompt user to authenticate with their email address.",
    "file": "authentication.json"
  },
  {
    "label": "Password Reset",
    "text": "Only use if no other option is available.",
    "file": "password_reset.json"
  },
  {
    "label": "Credit Card Offer",
    "text": "Credit card limit to $7,000 for credit cards with a limit of less than $5,000",
    "file": "card_offer.json"
  },
  {
    "label": "Create Account (Owl Shoes)",
    "text": "Create a brand new account for first time users",
    "file": "create_account_owl_shoes.json"
  },
  {
    "label": "Confirm your order",
    "text": "Form to confirm order before payment is taken",
    "file": "order_confirmation.json"
  },
  {
    "label": "Disambiguate",
    "text": "Disambiguate between two or more options",
    "file": "disambiguate.json"
  },
  {
    "label": "Disambiguate Stack",
    "text": "Disambiguate between two or more options",
    "file": "disambiguate2.json"
  },
  {
    "label": "Manage Card Online",
    "text": "Simple instructions to manage your card online",
    "file": "manage_card_online.json"
  },
  {
    "label": "Proof of purchase",
    "text": "Form to request proof of purchase for a product or service",
    "file": "proof_of_purchase.json"
  },

  {
    "label": "Flight Update",
    "text": "Update on flight status for a user who has a flight booked",
    "file": "flight_update.json"
  },
  {
    "label": "Stock Price",
    "text": "Current stock price for Twilio company",
    "file": "stock_price.json"
  },
  {
    "label": "Product Video (Flex)",
    "text": "See Twilio Flex in action in this short video",
    "file": "product_video_flex.json"
  },
  {
    "label": "Current Weather",
    "text": "Current weather conditions for your location",
    "file": "weather.json"
  },
  {
    "label": "Today's Agenda",
    "text": "See what's on your agenda for today",
    "file": "agenda.json"
  },
  {
    "label": "PCI Payment Form",
    "text": "Secure form to take payment from a customer"
  },
  {
    "label": "Refund Request",
    "text": "Submit a refund request for a product or service"
  },
  {
    "label": "Compatibility Checker",
    "text": "Run tests on user device to ensure compatibility with our products"
  },
  {
    "label": "Speed Test",
    "text": "Run a speed test on the end users device, note if they are on wifi or cellular"
  },
  {
    "label": "Address Change (AU)",
    "text": "Form to change the users address, all post office fields must be completed"
  },
  {
    "label": "Address Change (International)",
    "text": "Form to change the users address for international customers"
  },
  {
    "label": "IT Service Request",
    "text": "Form to request services from the IT department"
  }
]
